{
  "_comment": "Sample QR payloads. Encode ONE object per QR sticker (see qr-generation-guide.md). The backend decodes these from the camera frame.",
  "products": [
    { "product": "Banana", "expiry": "2026-05-22" },
    { "product": "Apple", "expiry": "2026-06-05" },
    { "product": "Tomato", "expiry": "2026-05-24" },
    { "product": "Cucumber", "expiry": "2026-05-23" },
    { "product": "Milk", "expiry": "2026-05-25" },
    { "product": "Yogurt", "expiry": "2026-05-28" },
    { "product": "Cheese", "expiry": "2026-06-15" },
    { "product": "Eggs", "expiry": "2026-06-01" },
    { "product": "Packaged Food", "expiry": "2026-09-30" }
  ]
}
